{
	"animations": [
		{
			"offsets": [
				0,
				90
			],
			"indices": [],
			"fps": 24,
			"anim": "idle",
			"loop": false,
			"name": "pico comic idle"
		},
		{
			"offsets": [
				0,
				90
			],
			"indices": [],
			"fps": 24,
			"anim": "singLEFT",
			"loop": false,
			"name": "pico comic left"
		},
		{
			"offsets": [
				0,
				90
			],
			"indices": [],
			"fps": 24,
			"anim": "singUP",
			"loop": false,
			"name": "pico comic up"
		},
		{
			"offsets": [
				0,
				90
			],
			"indices": [],
			"fps": 24,
			"anim": "singRIGHT",
			"loop": false,
			"name": "pico comic right"
		},
		{
			"offsets": [
				0,
				90
			],
			"indices": [],
			"fps": 24,
			"anim": "singDOWN",
			"loop": false,
			"name": "pico comic down"
		}
	],
	"no_antialiasing": false,
	"image": "characters/picoComic",
	"position": [
		1450,
		50
	],
	"healthicon": "picoGB",
	"flip_x": true,
	"healthbar_colors": [
		253,
		105,
		34
	],
	"camera_position": [
		100,
		0
	],
	"sing_duration": 4,
	"scale": 1.3
}